py3_ready/__init__.py
py3_ready/apt_tracer.py
py3_ready/cli.py
py3_ready/dependency_tracer.py
py3_ready/dot.py
py3_ready/package_xml.py
py3_ready/rosdep.py
py3_ready-0.1.0.dist-info/LICENSE
py3_ready-0.1.0.dist-info/METADATA
py3_ready-0.1.0.dist-info/WHEEL
py3_ready-0.1.0.dist-info/entry_points.txt
py3_ready-0.1.0.dist-info/top_level.txt
py3_ready-0.1.0.dist-info/RECORD
