Metadata-Version: 2.1
Name: py3-ready
Version: 0.1.0
Summary: A tool to identify dependencies on python 2.
Home-page: https://github.com/osrf/py3-ready
Author: Shane Loretz
Author-email: sloretz@openrobotics.org
License: Apache License 2.0
Platform: UNKNOWN
Classifier: Programming Language :: Python
Classifier: Programming Language :: Python :: 3
Classifier: Programming Language :: Python :: 2
Classifier: License :: OSI Approved :: Apache Software License
